Workbook

Sheet README
A1: FCFCU FORENSIC ACCOUNTING WORKBOOK
A2: Purpose | B2: Separate the supportable number from the plaintiff's shifting number; then force every change into an account-coded journal and general ledger.
A3: How to use | B3: 1) Start in Inputs_Calc. 2) Enter any newly verified publications / sheriff fees / taxes / insurance. 3) Add each later filing to Claims_Timeline. 4) Classify each new delta in Change_Classifier. 5) Review GL_Real, GL_Claim_Changes, and Comparison.
A4: Early read | B4: The RFA amounts as of 2024-11-19 roll exactly to the May 28, 2025 judgment loan components using 161 days of per-diem interest. The workbook also isolates the later 30-day extra-interest issue and the post-judgment gap to the sheriff-sale return.
A5: Core outputs
B6: Inputs_Calc | C6: Derives the supportable reconstructed amount and the unexplained gap.
B7: Reconstructed_Journal + GL_Real | C7: Shows the supportable charge stack by account.
B8: Claims_Timeline + Change_Classifier + GL_Claim_Changes | C8: Shows how their numbers changed from filing to filing.
B9: Comparison | C9: Shows the gap they still have to explain with documents.

Sheet Source_Map
A1: Source_ID | B1: Doc/Filing Date | C1: Document | D1: Key Figures Captured | E1: Use in Workbook | F1: Status
A2: S1 | B2: 45673 | C2: Request for Admissions | D2: L1 $190,685.22; L2 $22,567.41; per diem $23.14 + $4.31 as of 2024-11-19 | E2: Opening claim / accrual basis | F2: Loaded
A3: S2 | B3: 45790 | C3: Affidavit / Default package | D3: Confirms affidavit package exists; use when extracting exact affidavit language | E3: Cross-check package | F3: Loaded
A4: S3 | B4: 45805 | C4: Amended Default Judgment | D4: L1 $194,410.76; L2 $23,261.32; court costs $191.01; attorney fees $3,000.00; total $220,863.09; plus additional interest from 2025-04-29 to judgment | E4: Judgment snapshot | F4: Loaded
A5: S4 | B5: 45909 | C5: Decree of Foreclosure Returned | D5: Sheriff sale fully satisfied; total paid $240,464.20 | E5: Sale return snapshot | F5: Loaded
A6: S5 | B6: 46008 | C6: Report to Sheriff's Sale and Report of No Excess Proceeds | D6: Later no-surplus position referenced in case summary | E6: Pending exact amount extraction | F6: Pending detail
A7: S6 | B7: 46077 | C7: Petition Determining No Surplus | D7: Document exists in archive tree | E7: Pending exact amount extraction | F7: Pending detail
A8: S7 | B8: 46079 | C8: Order on Surplus and Nunc Pro Tunc | D8: Document exists in archive tree | E8: Pending exact amount extraction | F8: Pending detail
A9: S8 | B9: 46083 | C9: Order to Pay Surplus Funds | D9: Document exists in archive tree | E9: Pending exact amount extraction | F9: Pending detail

Sheet Inputs_Calc
A1: FCFCU SUPPORTABLE NUMBER CALCULATOR | E1: DERIVED METRICS | F1: Value
A2: Case Dates
A3: RFA as-of date | B3: 45615 | E3: Days from 2024-11-19 to 2025-04-29 | F3: =B4-B3 -> 161
A4: Accrual cutoff used by judgment components | B4: 45776 | E4: Accrued Loan 1 to 2025-04-29 | F4: =F3*B10 -> 3725.54
A5: Judgment date | B5: 45805 | E5: Accrued Loan 2 to 2025-04-29 | F5: =F3*B11 -> 693.91
A6: Sheriff sale date | B6: 45884 | E6: Reconstructed subtotal at 2025-04-29 | F6: =SUM(B7:B8,F4:F5) -> 195104.67
A7: RFA / Judgment Inputs | E7: Reconstructed total matching judgment components | F7: =F6+B13+B14 -> 198295.68
A8: Loan 1 RFA amount | B8: 190685.22 | E8: Difference vs judgment stated total | F8: =B15-F7 -> 22567.41
A9: Loan 2 RFA amount | B9: 22567.41
A10: Loan 1 per diem | B10: 23.14 | E10: Judgment days exclusive (2025-05-28 - 2025-04-29) | F10: =B5-B4 -> 29
A11: Loan 2 per diem | B11: 4.31 | E11: Judgment days inclusive | F11: =B5-B4+1 -> 30
A12: Judgment Inputs | E12: Selected judgment extra days | F12: =F10 -> 29
A13: Judgment court costs | B13: 191.01 | E13: Selected extra interest Loan 1 | F13: =F12*B10 -> 671.06
A14: Judgment attorney fees | B14: 3000 | E14: Selected extra interest Loan 2 | F14: =F12*B11 -> 124.99
A15: Judgment stated total | B15: 220863.09 | E15: Selected extra interest total | F15: =SUM(F13:F14) -> 796.05
A16: Sale return total paid | B16: 240464.2 | E16: Reconstructed total incl selected extra interest | F16: =F7+F15 -> 199091.73
A17: Optional verified post-judgment costs | E17: Gap between sale return and reconstructed total | F17: =B16-F16 -> 41372.47
A18: Publication costs (enter when sourced) | B18: 0 | E18: Gap between sale return and naked judgment total | F18: =B16-B15 -> 19601.11
A19: Sheriff sale costs (enter when sourced) | B19: 0 | E19: Known post-judgment costs entered below | F19: =SUM(B18:B20) -> 0
A20: Taxes / insurance advances (enter when sourced) | B20: 0 | E20: Remaining unexplained gap after entered costs | F20: =F17-F19 -> 41372.47
A22: Interpretation note | B22: If F8 = 0.00, the May 28 judgment loan buckets tie exactly to the November 19, 2024 RFA amounts plus 161 days of per-diem interest. F20 is the amount they still need documents to explain if they want to erase surplus.

Sheet Accounts
A1: Account Code | B1: Account Name | C1: Class | D1: Use
A2: 1000 | B2: Loan 1 claimed indebtedness | C2: Claim | D2: Opening or stated Loan 1 amount
A3: 1010 | B3: Loan 2 claimed indebtedness | C3: Claim | D3: Opening or stated Loan 2 amount
A4: 1100 | B4: Accrued interest adjustment - Loan 1 | C4: Accrual | D4: Interest layer tied to Loan 1
A5: 1110 | B5: Accrued interest adjustment - Loan 2 | C5: Accrual | D5: Interest layer tied to Loan 2
A6: 1200 | B6: Court costs | C6: Cost | D6: Court costs or filing costs
A7: 1210 | B7: Attorney fees | C7: Fee | D7: Attorney fee claim
A8: 1220 | B8: Publication costs | C8: Cost | D8: Publication / notice publication costs
A9: 1230 | B9: Sheriff sale costs | C9: Cost | D9: Sheriff sale fees and related sale costs
A10: 1240 | B10: Taxes and insurance advances | C10: Advance | D10: Taxes, insurance, or protective advances
A11: 1250 | B11: Unexplained / unsupported adjustments | C11: Forensic | D11: Residual amount not yet tied to documents
A12: 2999 | B12: Case offset / suspense | C12: Offset | D12: Balancing credit for analytical journal entries

Sheet Reconstructed_Journal
A1: Date | B1: Source_ID | C1: Entry_Group | D1: Debit_Acct | E1: Debit_Name | F1: Credit_Acct | G1: Credit_Name | H1: Amount | I1: Formula_Work | J1: Support_Status | K1: Notes
A2: 45615 | B2: S1 | C2: OPEN | D2: 1000 | E2: Loan 1 claimed indebtedness | F2: 2999 | G2: Case offset / suspense | H2: =Inputs_Calc!B8 -> 190685.22 | I2: RFA opening Loan 1 claim | J2: Loaded | K2: As of 2024-11-19
A3: 45615 | B3: S1 | C3: OPEN | D3: 1010 | E3: Loan 2 claimed indebtedness | F3: 2999 | G3: Case offset / suspense | H3: =Inputs_Calc!B9 -> 22567.41 | I3: RFA opening Loan 2 claim | J3: Loaded | K3: As of 2024-11-19
A4: 45776 | B4: CALC | C4: ACCRUAL | D4: 1100 | E4: Accrued interest adjustment - Loan 1 | F4: 2999 | G4: Case offset / suspense | H4: =Inputs_Calc!F4 -> 3725.54 | I4: 161 days * Loan 1 per diem | J4: Derived | K4: Brings Loan 1 from RFA to 2025-04-29
A5: 45776 | B5: CALC | C5: ACCRUAL | D5: 1110 | E5: Accrued interest adjustment - Loan 2 | F5: 2999 | G5: Case offset / suspense | H5: =Inputs_Calc!F5 -> 693.91 | I5: 161 days * Loan 2 per diem | J5: Derived | K5: Brings Loan 2 from RFA to 2025-04-29
A6: 45805 | B6: S3 | C6: COST | D6: 1200 | E6: Court costs | F6: 2999 | G6: Case offset / suspense | H6: =Inputs_Calc!B13 -> 191.01 | I6: Judgment court costs | J6: Loaded | K6: From amended default judgment
A7: 45805 | B7: S3 | C7: FEE | D7: 1210 | E7: Attorney fees | F7: 2999 | G7: Case offset / suspense | H7: =Inputs_Calc!B14 -> 3000 | I7: Judgment attorney fees | J7: Loaded | K7: From amended default judgment
A8: 45805 | B8: S3/CALC | C8: EXTRA_INT | D8: 1100 | E8: Accrued interest adjustment - Loan 1 | F8: 2999 | G8: Case offset / suspense | H8: =Inputs_Calc!F13 -> 671.06 | I8: Selected judgment extra-interest days * Loan 1 per diem | J8: Derived | K8: Default set to inclusive 30-day count
A9: 45805 | B9: S3/CALC | C9: EXTRA_INT | D9: 1110 | E9: Accrued interest adjustment - Loan 2 | F9: 2999 | G9: Case offset / suspense | H9: =Inputs_Calc!F14 -> 124.99 | I9: Selected judgment extra-interest days * Loan 2 per diem | J9: Derived | K9: Default set to inclusive 30-day count
A10: 45884 | B10: USER | C10: POSTJG_COST | D10: 1220 | E10: Publication costs | F10: 2999 | G10: Case offset / suspense | H10: =Inputs_Calc!B18 -> 0 | I10: Enter only when sourced | J10: Pending | K10: Currently zero until verified
A11: 45884 | B11: USER | C11: POSTJG_COST | D11: 1230 | E11: Sheriff sale costs | F11: 2999 | G11: Case offset / suspense | H11: =Inputs_Calc!B19 -> 0 | I11: Enter only when sourced | J11: Pending | K11: Currently zero until verified
A12: 45884 | B12: USER | C12: POSTJG_COST | D12: 1240 | E12: Taxes and insurance advances | F12: 2999 | G12: Case offset / suspense | H12: =Inputs_Calc!B20 -> 0 | I12: Enter only when sourced | J12: Pending | K12: Currently zero until verified
A13: 45884 | B13: AUTO | C13: RESIDUAL | D13: 1250 | E13: Unexplained / unsupported adjustments | F13: 2999 | G13: Case offset / suspense | H13: =Inputs_Calc!F20 -> 41372.47 | I13: Residual sale-return gap after all entered costs | J13: Forensic | K13: This is the bucket they still have to document

Sheet GL_Real
A1: Account Code | B1: Account Name | C1: GL Amount | D1: Entry Count | E1: Notes
A2: 1000 | B2: Loan 1 claimed indebtedness | C2: =SUMIFS(Reconstructed_Journal!$H:$H,Reconstructed_Journal!$D:$D,A2) -> 190685.22 | D2: =COUNTIFS(Reconstructed_Journal!$D:$D,A2) -> 1 | E2: Opening claim only; accrual layers sit in 1100
A3: 1010 | B3: Loan 2 claimed indebtedness | C3: =SUMIFS(Reconstructed_Journal!$H:$H,Reconstructed_Journal!$D:$D,A3) -> 22567.41 | D3: =COUNTIFS(Reconstructed_Journal!$D:$D,A3) -> 1 | E3: Opening claim only; accrual layers sit in 1110
A4: 1100 | B4: Accrued interest adjustment - Loan 1 | C4: =SUMIFS(Reconstructed_Journal!$H:$H,Reconstructed_Journal!$D:$D,A4) -> 4396.6 | D4: =COUNTIFS(Reconstructed_Journal!$D:$D,A4) -> 2 | E4: Pre-4/29 accrual plus selected extra-interest layer
A5: 1110 | B5: Accrued interest adjustment - Loan 2 | C5: =SUMIFS(Reconstructed_Journal!$H:$H,Reconstructed_Journal!$D:$D,A5) -> 818.9 | D5: =COUNTIFS(Reconstructed_Journal!$D:$D,A5) -> 2 | E5: Pre-4/29 accrual plus selected extra-interest layer
A6: 1200 | B6: Court costs | C6: =SUMIFS(Reconstructed_Journal!$H:$H,Reconstructed_Journal!$D:$D,A6) -> 191.01 | D6: =COUNTIFS(Reconstructed_Journal!$D:$D,A6) -> 1 | E6: From judgment
A7: 1210 | B7: Attorney fees | C7: =SUMIFS(Reconstructed_Journal!$H:$H,Reconstructed_Journal!$D:$D,A7) -> 3000 | D7: =COUNTIFS(Reconstructed_Journal!$D:$D,A7) -> 1 | E7: From judgment
A8: 1220 | B8: Publication costs | C8: =SUMIFS(Reconstructed_Journal!$H:$H,Reconstructed_Journal!$D:$D,A8) -> 0 | D8: =COUNTIFS(Reconstructed_Journal!$D:$D,A8) -> 1 | E8: User-enter once sourced
A9: 1230 | B9: Sheriff sale costs | C9: =SUMIFS(Reconstructed_Journal!$H:$H,Reconstructed_Journal!$D:$D,A9) -> 0 | D9: =COUNTIFS(Reconstructed_Journal!$D:$D,A9) -> 1 | E9: User-enter once sourced
A10: 1240 | B10: Taxes and insurance advances | C10: =SUMIFS(Reconstructed_Journal!$H:$H,Reconstructed_Journal!$D:$D,A10) -> 0 | D10: =COUNTIFS(Reconstructed_Journal!$D:$D,A10) -> 1 | E10: User-enter once sourced
A11: 1250 | B11: Unexplained / unsupported adjustments | C11: =SUMIFS(Reconstructed_Journal!$H:$H,Reconstructed_Journal!$D:$D,A11) -> 41372.47 | D11: =COUNTIFS(Reconstructed_Journal!$D:$D,A11) -> 1 | E11: Residual they still have to prove
B12: TOTAL SUPPORTABLE / FORENSIC CHARGE STACK | C12: =SUM(C2:C11) -> 263031.61 | E12: Should tie to Inputs_Calc!F16 + entered post-judgment costs + residual

Sheet Claims_Timeline
A1: Version# | B1: Source_ID | C1: Doc Date | D1: Document | E1: Loan 1 | F1: Loan 2 | G1: Court Costs | H1: Attorney Fees | I1: Other / Extra Interest | J1: Other Costs / Advances | K1: Total Asserted | L1: Delta vs Prior | M1: Delta % | N1: Classification Note | O1: Status
A2: 1 | B2: S1 | C2: 45673 | D2: Request for Admissions (amounts stated as of 2024-11-19) | E2: 190685.22 | F2: 22567.41 | G2: 0 | H2: 0 | I2: 0 | J2: 0 | K2: =SUM(E2:J2) -> 213252.63 | N2: Opening snapshot only | O2: Loaded
A3: 2 | B3: S3 | C3: 45805 | D3: Amended Default Judgment | E3: 194410.76 | F3: 23261.32 | G3: 191.01 | H3: 3000 | I3: 0 | J3: 0 | K3: 220863.09 | L3: =K3-K2 -> 7610.46 | M3: =IF(K2=0,"",L3/K2) -> 0.035687532 | N3: Text also states extra interest from 2025-04-29 to judgment | O3: Loaded
A4: 3 | B4: S4 | C4: 45909 | D4: Decree of Foreclosure Returned / fully satisfied by sheriff sale | E4: 0 | F4: 0 | G4: 0 | H4: 0 | I4: 0 | J4: 0 | K4: 240464.2 | L4: =K4-K3 -> 19601.11 | M4: =IF(K3=0,"",L4/K3) -> 0.088747785 | N4: Total paid only; bucket split pending | O4: Loaded
A5: 4 | B5: S5 | C5: 46008 | D5: Report to Sheriff's Sale and Report of No Excess Proceeds | E5: 0 | F5: 0 | G5: 0 | H5: 0 | I5: 0 | J5: 0 | L5: =IF(K5="","",K5-K4) | M5: =IF(OR(K5="",K4=0),"",L5/K4) | N5: Enter exact no-excess figure once extracted | O5: Pending detail
A6: 5 | B6: S6 | C6: 46077 | D6: Petition Determining No Surplus | E6: 0 | F6: 0 | G6: 0 | H6: 0 | I6: 0 | J6: 0 | L6: =IF(K6="","",K6-K5) | M6: =IF(OR(K6="",K5=0),"",L6/K5) | N6: Enter exact petition number once extracted | O6: Pending detail
A7: 6 | B7: S7 | C7: 46079 | D7: Order on Surplus and Nunc Pro Tunc | E7: 0 | F7: 0 | G7: 0 | H7: 0 | I7: 0 | J7: 0 | L7: =IF(K7="","",K7-K6) | M7: =IF(OR(K7="",K6=0),"",L7/K6) | N7: Enter exact court figure once extracted | O7: Pending detail
A8: 7 | B8: S8 | C8: 46083 | D8: Order to Pay Surplus Funds | E8: 0 | F8: 0 | G8: 0 | H8: 0 | I8: 0 | J8: 0 | L8: =IF(K8="","",K8-K7) | M8: =IF(OR(K8="",K7=0),"",L8/K7) | N8: Enter exact paid / ordered surplus figure once extracted | O8: Pending detail

Sheet Change_Classifier
A1: Date | B1: Version# | C1: Source_ID | D1: Account Code | E1: Account Name | F1: Amount Change | G1: Basis | H1: Support_Status | I1: Notes
A2: 45805 | B2: 2 | C2: S3 | D2: 1100 | E2: Accrued interest adjustment - Loan 1 | F2: =Claims_Timeline!E3-Claims_Timeline!E2 -> 3725.54 | G2: Loan 1 increase from RFA to judgment | H2: Loaded | I2: Ties exactly to 161 days * $23.14
A3: 45805 | B3: 2 | C3: S3 | D3: 1110 | E3: Accrued interest adjustment - Loan 2 | F3: =Claims_Timeline!F3-Claims_Timeline!F2 -> 693.91 | G3: Loan 2 increase from RFA to judgment | H3: Loaded | I3: Ties exactly to 161 days * $4.31
A4: 45805 | B4: 2 | C4: S3 | D4: 1200 | E4: Court costs | F4: =Claims_Timeline!G3-Claims_Timeline!G2 -> 191.01 | G4: Court costs added at judgment | H4: Loaded
A5: 45805 | B5: 2 | C5: S3 | D5: 1210 | E5: Attorney fees | F5: =Claims_Timeline!H3-Claims_Timeline!H2 -> 3000 | G5: Attorney fees added at judgment | H5: Loaded
A6: 45909 | B6: 3 | C6: S4 | D6: 1250 | E6: Unexplained / unsupported adjustments | F6: =Claims_Timeline!K4-Claims_Timeline!K3 -> 19601.11 | G6: Sale-return increase over judgment snapshot | H6: Forensic | I6: This is the first big unexplained jump unless later allocated to proven costs
A7: 46008 | B7: 4 | C7: S5 | D7: 1250 | E7: Unexplained / unsupported adjustments | F7: =IF(Claims_Timeline!K5="","",Claims_Timeline!K5-Claims_Timeline!K4) | G7: No-excess report delta vs prior snapshot | H7: Pending detail | I7: Fill once exact amount extracted
A8: 46077 | B8: 5 | C8: S6 | D8: 1250 | E8: Unexplained / unsupported adjustments | F8: =IF(Claims_Timeline!K6="","",Claims_Timeline!K6-Claims_Timeline!K5) | G8: Petition no-surplus delta vs prior snapshot | H8: Pending detail | I8: Fill once exact amount extracted
A9: 46079 | B9: 6 | C9: S7 | D9: 1250 | E9: Unexplained / unsupported adjustments | F9: =IF(Claims_Timeline!K7="","",Claims_Timeline!K7-Claims_Timeline!K6) | G9: Order on surplus / nunc pro tunc delta vs prior snapshot | H9: Pending detail | I9: Fill once exact amount extracted
A10: 46083 | B10: 7 | C10: S8 | D10: 2100 | E10: Surplus payable | F10: =IF(Claims_Timeline!K8="","",Claims_Timeline!K8-Claims_Timeline!K7) | G10: Order to pay surplus funds delta vs prior snapshot | H10: Pending detail | I10: Use positive number for surplus ordered / recognized

Sheet GL_Claim_Changes
A1: Account Code | B1: Account Name | C1: Change Ledger Amount | D1: Entry Count | E1: Notes
A2: 1100 | B2: Accrued interest adjustment - Loan 1 | C2: =SUMIFS(Change_Classifier!$F:$F,Change_Classifier!$D:$D,A2) -> 3725.54 | D2: =COUNTIFS(Change_Classifier!$D:$D,A2) -> 1 | E2: Version-to-version changes only
A3: 1110 | B3: Accrued interest adjustment - Loan 2 | C3: =SUMIFS(Change_Classifier!$F:$F,Change_Classifier!$D:$D,A3) -> 693.91 | D3: =COUNTIFS(Change_Classifier!$D:$D,A3) -> 1 | E3: Version-to-version changes only
A4: 1200 | B4: Court costs | C4: =SUMIFS(Change_Classifier!$F:$F,Change_Classifier!$D:$D,A4) -> 191.01 | D4: =COUNTIFS(Change_Classifier!$D:$D,A4) -> 1 | E4: Version-to-version changes only
A5: 1210 | B5: Attorney fees | C5: =SUMIFS(Change_Classifier!$F:$F,Change_Classifier!$D:$D,A5) -> 3000 | D5: =COUNTIFS(Change_Classifier!$D:$D,A5) -> 1 | E5: Version-to-version changes only
A6: 1250 | B6: Unexplained / unsupported adjustments | C6: =SUMIFS(Change_Classifier!$F:$F,Change_Classifier!$D:$D,A6) -> 19601.11 | D6: =COUNTIFS(Change_Classifier!$D:$D,A6) -> 4 | E6: This is where their moving target shows up first
A7: 2100 | B7: Surplus payable | C7: =SUMIFS(Change_Classifier!$F:$F,Change_Classifier!$D:$D,A7) -> 0 | D7: =COUNTIFS(Change_Classifier!$D:$D,A7) -> 1 | E7: Populate once the court-ordered surplus figure is entered
B8: TOTAL PLAINTIFF VERSION-TO-VERSION CHANGE STACK | C8: =SUM(C2:C7) -> 27211.57 | E8: Should approximate latest asserted total less opening snapshot, once all later figures are filled

Sheet Comparison
A1: COMPARISON METRIC | B1: Value | C1: Meaning
A2: Opening RFA claim total | B2: =Claims_Timeline!K2 -> 213252.63 | C2: Their earliest loaded numeric snapshot
A3: Judgment stated total (without extra-interest bucket) | B3: =Claims_Timeline!K3 -> 220863.09 | C3: The May 28, 2025 judgment number in the order
A4: Reconstructed total incl selected judgment extra interest | B4: =Inputs_Calc!F16 -> 199091.73 | C4: Supportable total using RFA + 161-day accrual + court costs + attorney fees + selected extra-interest days
A5: Sheriff-sale return total paid | B5: =Claims_Timeline!K4 -> 240464.2 | C5: The September 9, 2025 fully satisfied sale-return figure
A6: Amount requiring documentary support to erase surplus | B6: =Inputs_Calc!F20 -> 41372.47 | C6: Residual post-judgment amount not yet tied to publications, sheriff fees, taxes, insurance, or another source-backed charge
A7: Sale-return jump over judgment stated total | B7: =Inputs_Calc!F18 -> 19601.11 | C7: Bigger version-to-version jump if you ignore the extra-interest layer completely
A8: Judgment-vs-reconstruction tie check | B8: =Inputs_Calc!F8 -> 22567.41 | C8: If zero, the judgment loan components exactly match the 161-day accrual math from the RFA base
A9: Current user-entered verified post-judgment costs | B9: =Inputs_Calc!F19 -> 0 | C9: Only costs you have actually sourced and entered
